{
  "data": [
    {
      "display": "Hamburgalerswag",
      "handle": "Hamburgalerswag",
      "image": "https://cdn.robertsspaceindustries.com/static/images/account/avatar_default_big.jpg",
      "rank": "Ensign",
      "roles": [],
      "stars": 0
    },
    {
      "display": "Johnnyboi90",
      "handle": "Johnnyboi90",
      "image": "https://cdn.robertsspaceindustries.com/static/images/account/avatar_default_big.jpg",
      "rank": "Ensign",
      "roles": [],
      "stars": 0
    },
    {
      "display": "Skelliem",
      "handle": "Skelliem",
      "image": "https://cdn.robertsspaceindustries.com/static/images/account/avatar_default_big.jpg",
      "rank": "Corporal",
      "roles": [
        "Recruiter"
      ],
      "stars": 1
    },
    {
      "display": "Zalinto",
      "handle": "Zalinto",
      "image": "https://robertsspaceindustries.com/media/2m09619y1ykgqr/avatar/BWr3m4J.png",
      "rank": "Commander",
      "roles": [],
      "stars": 3
    },
    {
      "display": "Catmenow1",
      "handle": "Catmenow1",
      "image": "https://cdn.robertsspaceindustries.com/static/images/account/avatar_default_big.jpg",
      "rank": "Lieutenant",
      "roles": [
        "Recruiter"
      ],
      "stars": 2
    },
    {
      "display": "killjoyy",
      "handle": "killjoyy",
      "image": "https://cdn.robertsspaceindustries.com/static/images/account/avatar_default_big.jpg",
      "rank": "Lieutenant",
      "roles": [],
      "stars": 2
    },
    {
      "display": "Mitch_Dragnas",
      "handle": "Mitch_Dragnas",
      "image": "https://cdn.robertsspaceindustries.com/static/images/account/avatar_default_big.jpg",
      "rank": "Corporal",
      "roles": [],
      "stars": 1
    },
    {
      "display": "Agrun225",
      "handle": "Agrun225",
      "image": "https://cdn.robertsspaceindustries.com/static/images/account/avatar_default_big.jpg",
      "rank": "Corporal",
      "roles": [],
      "stars": 1
    },
    {
      "display": "ZacZulu",
      "handle": "ZacZulu",
      "image": "https://cdn.robertsspaceindustries.com/static/images/account/avatar_default_big.jpg",
      "rank": "Corporal",
      "roles": [],
      "stars": 1
    },
    {
      "display": "Kinderpuk",
      "handle": "Kinderpuk",
      "image": "https://cdn.robertsspaceindustries.com/static/images/account/avatar_default_big.jpg",
      "rank": "Corporal",
      "roles": [],
      "stars": 1
    },
    {
      "display": "GummyBear_Warlord",
      "handle": "GummyBear_Warlord",
      "image": "https://cdn.robertsspaceindustries.com/static/images/account/avatar_default_big.jpg",
      "rank": "Corporal",
      "roles": [],
      "stars": 1
    },
    {
      "display": "Tazz",
      "handle": "CitizenTAZZ",
      "image": "https://cdn.robertsspaceindustries.com/static/images/account/avatar_default_big.jpg",
      "rank": "Lieutenant",
      "roles": [
        "Recruiter"
      ],
      "stars": 2
    },
    {
      "display": "korinna",
      "handle": "korinna",
      "image": "https://cdn.robertsspaceindustries.com/static/images/account/avatar_default_big.jpg",
      "rank": "Corporal",
      "roles": [],
      "stars": 1
    },
    {
      "display": "Dopuhmean",
      "handle": "Dopuhmean",
      "image": "https://cdn.robertsspaceindustries.com/static/images/account/avatar_default_big.jpg",
      "rank": "Corporal",
      "roles": [
        "Recruiter"
      ],
      "stars": 1
    },
    {
      "display": "MysticMist07",
      "handle": "Bean_Daddy",
      "image": "https://robertsspaceindustries.com/media/l6f8wb58jc9wir/avatar/Estinien_Heavensward_art-8929.jpg",
      "rank": "Corporal",
      "roles": [],
      "stars": 1
    },
    {
      "display": "Deather132",
      "handle": "Deather132",
      "image": "https://cdn.robertsspaceindustries.com/static/images/account/avatar_default_big.jpg",
      "rank": "Corporal",
      "roles": [
        "Recruiter"
      ],
      "stars": 1
    },
    {
      "display": "kahuna26",
      "handle": "kahuna26",
      "image": "https://cdn.robertsspaceindustries.com/static/images/account/avatar_default_big.jpg",
      "rank": "Corporal",
      "roles": [
        "Recruiter"
      ],
      "stars": 1
    },
    {
      "display": "BlazeGod",
      "handle": "BlazeGod",
      "image": "https://cdn.robertsspaceindustries.com/static/images/account/avatar_default_big.jpg",
      "rank": "Corporal",
      "roles": [],
      "stars": 1
    },
    {
      "display": "Axtt17",
      "handle": "Axtt17",
      "image": "https://cdn.robertsspaceindustries.com/static/images/account/avatar_default_big.jpg",
      "rank": "Lieutenant",
      "roles": [],
      "stars": 2
    },
    {
      "display": "DizzyDevils",
      "handle": "DizzyDevils",
      "image": "https://cdn.robertsspaceindustries.com/static/images/account/avatar_default_big.jpg",
      "rank": "Lieutenant",
      "roles": [],
      "stars": 2
    },
    {
      "display": "Reshala",
      "handle": "BilboFraggin",
      "image": "https://cdn.robertsspaceindustries.com/static/images/account/avatar_default_big.jpg",
      "rank": "Commander",
      "roles": [
        "Officer",
        "Recruiter",
        "Branding"
      ],
      "stars": 3
    },
    {
      "display": "Desolvezz",
      "handle": "Desolvezz",
      "image": "https://cdn.robertsspaceindustries.com/static/images/account/avatar_default_big.jpg",
      "rank": "Corporal",
      "roles": [],
      "stars": 1
    },
    {
      "display": "st3vie",
      "handle": "st3vie",
      "image": "https://robertsspaceindustries.com/media/7qhqg8w6futq0r/avatar/The_last_ninja.jpg",
      "rank": "Corporal",
      "roles": [
        "Recruiter"
      ],
      "stars": 1
    },
    {
      "display": "LockJawLaw",
      "handle": "LockJawLaw",
      "image": "https://cdn.robertsspaceindustries.com/static/images/account/avatar_default_big.jpg",
      "rank": "Admiral",
      "roles": [
        "Officer",
        "Recruiter"
      ],
      "stars": 4
    },
    {
      "display": "ZombieLove",
      "handle": "ZombieLove",
      "image": "https://cdn.robertsspaceindustries.com/static/images/account/avatar_default_big.jpg",
      "rank": "Corporal",
      "roles": [],
      "stars": 1
    },
    {
      "display": "ElgranMonke",
      "handle": "ElgranMonke",
      "image": "https://cdn.robertsspaceindustries.com/static/images/account/avatar_default_big.jpg",
      "rank": "Corporal",
      "roles": [
        "Recruiter"
      ],
      "stars": 1
    },
    {
      "display": "Brolt-X",
      "handle": "Brolt-X",
      "image": "https://cdn.robertsspaceindustries.com/static/images/account/avatar_default_big.jpg",
      "rank": "Lieutenant",
      "roles": [
        "Recruiter"
      ],
      "stars": 2
    },
    {
      "display": "MrWolfingerYT",
      "handle": "MrWolfingerYT",
      "image": "https://cdn.robertsspaceindustries.com/static/images/account/avatar_default_big.jpg",
      "rank": "Corporal",
      "roles": [
        "Recruiter"
      ],
      "stars": 1
    },
    {
      "display": "BEANS",
      "handle": "Lil_BEANS",
      "image": "https://cdn.robertsspaceindustries.com/static/images/account/avatar_default_big.jpg",
      "rank": "Lieutenant",
      "roles": [
        "Recruiter"
      ],
      "stars": 2
    },
    {
      "display": "El Quedro",
      "handle": "El_Quedro",
      "image": "https://robertsspaceindustries.com/media/xxc69imdypqbwr/avatar/Bender-Avatar.jpg",
      "rank": "Admiral",
      "roles": [
        "Founder",
        "Officer",
        "Recruiter",
        "Branding"
      ],
      "stars": 4
    },
    {
      "display": "HolyPenguins",
      "handle": "HolyPenguins",
      "image": "https://cdn.robertsspaceindustries.com/static/images/account/avatar_default_big.jpg",
      "rank": "Admiral",
      "roles": [
        "Officer"
      ],
      "stars": 4
    },
    {
      "display": "Sarlos",
      "handle": "Sarlos",
      "image": "https://robertsspaceindustries.com/media/z956clf9etn1br/avatar/Major-Tom.jpg",
      "rank": "Admiral",
      "roles": [],
      "stars": 4
    }
  ],
  "message": "ok",
  "source": "live",
  "success": 1
}
